{"nodes": [{"is_core": false, "source": [{"holder": "1", "name": "MEC International Company Ltd."}], "name": "MEC Electronics Philippines Corporation", "no_holder": false, "taxcode": "NA"}, {"is_core": false, "source": [{"holder": "0.4", "name": "MEC Electronics Philippines Corporation"}], "name": "Chiao Lin Electronics", "no_holder": false, "taxcode": "NA"}, {"is_core": false, "source": [{"holder": "1", "name": "Dimerco Express Holding Co., Ltd."}], "name": "Dimerco Express (Malaysia) Sdn. Bhd.", "no_holder": false, "taxcode": "NA"}, {"is_core": false, "source": [{"holder": "1", "name": "Dimerco Express (Malaysia) Sdn. Bhd."}], "name": "Danau Muhibbah Sdn. Bhd.", "no_holder": false, "taxcode": "NA"}, {"is_core": false, "source": [{"holder": "1", "name": "中菲行國際物流股份有限公司"}], "name": "Dimerco Interational Logistic Corp.", "no_holder": false, "taxcode": "NA"}, {"is_core": false, "source": [{"holder": "0.9999", "name": "Dimerco Interational Logistic Corp."}], "name": "Dimerco Air Forwarders (HK) Ltd.", "no_holder": false, "taxcode": "NA"}, {"is_core": false, "source": [{"holder": "1", "name": "Dimerco Interational Logistic Corp."}], "name": "Dimerco Express (U.S.A.) Corp.", "no_holder": false, "taxcode": "NA"}, {"is_core": false, "source": [{"holder": "1", "name": "Dimerco Express (U.S.A.) Corp."}], "name": "Dimerco Customs Brokerage Co. Ltd", "no_holder": false, "taxcode": "NA"}, {"is_core": false, "source": [{"holder": "1", "name": "中菲行國際物流股份有限公司"}], "name": "Dimerco Express Holding Co., Ltd.", "no_holder": false, "taxcode": "NA"}, {"is_core": false, "source": [{"holder": "1", "name": "Dimerco Express Holding Co., Ltd."}], "name": "Dimerco Express (Australia) Pty Ltd", "no_holder": false, "taxcode": "NA"}, {"is_core": false, "source": [{"holder": "1", "name": "Dimerco Express Holding Co., Ltd."}], "name": "Dimerco Express (Canada) Corp.", "no_holder": false, "taxcode": "NA"}, {"is_core": false, "source": [{"holder": "0.1389", "name": "Dimerco Interational Logistic Corp."}, {"holder": "0.8611", "name": "中菲行國際物流股份有限公司"}], "name": "Dimerco Express (Singapore) Pte Ltd.", "no_holder": false, "taxcode": "NA"}, {"is_core": false, "source": [{"holder": "0.5", "name": "Dimerco Express (Singapore) Pte Ltd."}], "name": "Dimerco Express (India) Pte Ltd.", "no_holder": false, "taxcode": "NA"}, {"is_core": false, "source": [{"holder": "1", "name": "Dimerco Express Holding Co., Ltd."}], "name": "Dimerco Express (Korea) Corp.", "no_holder": false, "taxcode": "NA"}, {"is_core": true, "source": [{"holder": "NA", "name": "龍翰興業股份有限公司"}], "name": "中菲行國際物流股份有限公司", "no_holder": false, "taxcode": "01176152"}, {"is_core": false, "source": [{"holder": "0.49", "name": "Dimerco Express Holding Co., Ltd."}], "name": "Dimerco Express (Thailand) Corp. Ltd.", "no_holder": false, "taxcode": "NA"}, {"is_core": false, "source": [{"holder": "1", "name": "Dimerco Interational Logistic Corp."}], "name": "Dimerco Express (U.K.) Ltd.", "no_holder": false, "taxcode": "NA"}, {"is_core": false, "source": [{"holder": "1", "name": "Dimerco Express Holding Co., Ltd."}], "name": "Dimerco Express Netherlands B.V.", "no_holder": false, "taxcode": "NA"}, {"is_core": false, "source": [{"holder": "0.4", "name": "Dimerco Express Holding Co., Ltd."}], "name": "Dimerco Express Phils. Inc.", "no_holder": false, "taxcode": "NA"}, {"is_core": false, "source": [{"holder": "0.49", "name": "Dimerco Express Holding Co., Ltd."}], "name": "Dimerco Logistics Sdn Bhd.", "no_holder": false, "taxcode": "NA"}, {"is_core": false, "name": "Dimerco Air Forwarders (HKG) Ltd.", "no_holder": false, "taxcode": "NA"}, {"is_core": false, "source": [{"holder": "0.75", "name": "Dimerco Air Forwarders (HKG) Ltd."}], "name": "Dimerco Vietfracht (JV) Co., Ltd.", "no_holder": false, "taxcode": "NA"}, {"is_core": false, "source": [{"holder": "0.99", "name": "Dimerco Express Holding Co., Ltd."}], "name": "Diversified Freight System Ltd.", "no_holder": false, "taxcode": "NA"}, {"is_core": false, "source": [{"holder": "1", "name": "Dimerco Express Holding Co., Ltd."}], "name": "Diversified International Service Logistics System Corporation", "no_holder": false, "taxcode": "NA"}, {"is_core": false, "source": [{"holder": "1", "name": "Diversified Freight System Ltd."}], "name": "Diversified International Transportation (Shanghai) Co., Ltd.", "no_holder": false, "taxcode": "NA"}, {"is_core": false, "source": [{"holder": "1", "name": "Dimerco Express Holding Co., Ltd."}], "name": "Diversified Transportation (HK & China) Co., Ltd.", "no_holder": false, "taxcode": "NA"}, {"is_core": false, "source": [{"holder": "1", "name": "Diversified Transportation (HK & China) Co., Ltd."}], "name": "Diversified Transportation (China) Co., Ltd.", "no_holder": false, "taxcode": "NA"}, {"is_core": false, "source": [{"holder": "0.2", "name": "Dimerco Air Forwarders (HKG) Ltd."}, {"holder": "0.2", "name": "Dimerco Express (Singapore) Pte Ltd."}, {"holder": "0.2", "name": "Dimerco Express (U.K.) Ltd."}, {"holder": "0.2", "name": "Dimerco Express (U.S.A.) Corp."}, {"holder": "0.2", "name": "中菲行國際物流股份有限公司"}], "name": "Foreign Settlement Co., Ltd.", "no_holder": false, "taxcode": "NA"}, {"is_core": false, "source": [{"holder": "1", "name": "Dimerco Interational Logistic Corp."}], "name": "Global Marketing System Co., Ltd.", "no_holder": false, "taxcode": "NA"}, {"is_core": false, "source": [{"holder": "1", "name": "MEC International Company Ltd."}], "name": "MEC Electronics (HK) Company Limited", "no_holder": false, "taxcode": "NA"}, {"is_core": false, "source": [{"holder": "1", "name": "MEC Electronics (HK) Company Limited"}], "name": "Homepride Technology Limited", "no_holder": false, "taxcode": "NA"}, {"is_core": false, "source": [{"holder": "1", "name": "維翰實業股份有限公司"}], "name": "MEC International Company Ltd.", "no_holder": false, "taxcode": "NA"}, {"is_core": false, "source": [{"holder": "1", "name": "MEC International Company Ltd."}], "name": "MEC Best Known Company Limited", "no_holder": false, "taxcode": "NA"}, {"is_core": false, "source": [{"holder": "1", "name": "MEC International Company Ltd."}], "name": "MEC Bloomtech Electronics (HK) Company Limited", "no_holder": false, "taxcode": "NA"}, {"is_core": false, "source": [{"holder": "1", "name": "MEC Electronics Philippines Corporation"}], "name": "MEC Imex (USA), Inc.", "no_holder": false, "taxcode": "NA"}, {"is_core": true, "source": [{"holder": "0.1412", "name": "龍翰興業股份有限公司"}], "name": "維翰實業股份有限公司", "no_holder": false, "taxcode": "NA"}, {"is_core": false, "source": [{"holder": "1", "name": "MEC International Company Ltd."}], "name": "MEC Ultramax (HK) Company Limited", "no_holder": false, "taxcode": "NA"}, {"is_core": false, "name": "龍翰興業股份有限公司", "no_holder": false, "taxcode": "12111831"}, {"is_core": false, "source": [{"holder": "1", "name": "Dimerco Air Forwarders (HK) Ltd."}], "name": "中菲行國際貨運代理(上海)有限公司", "no_holder": false, "taxcode": "NA"}, {"is_core": false, "source": [{"holder": "0.9999", "name": "Dimerco Air Forwarders (HK) Ltd."}], "name": "中菲物流(上海)有限公司", "no_holder": false, "taxcode": "NA"}, {"is_core": false, "source": [{"holder": "1", "name": "Dimerco Air Forwarders (HK) Ltd."}], "name": "中菲物流(深圳)有限公司", "no_holder": false, "taxcode": "NA"}, {"is_core": false, "source": [{"holder": "0.75", "name": "Dimerco Air Forwarders (HK) Ltd."}], "name": "中經得美國際快運代理有限公司", "no_holder": false, "taxcode": "NA"}, {"is_core": false, "source": [{"holder": "0.9999", "name": "中菲行國際物流股份有限公司"}], "name": "得美行股份有限公司", "no_holder": false, "taxcode": "04378245"}, {"is_core": false, "source": [{"holder": "1", "name": "Homepride Technology Limited"}], "name": "僑達電子(東莞)有限公司", "no_holder": false, "taxcode": "NA"}, {"is_core": false, "source": [{"holder": "1", "name": "MEC Bloomtech Electronics (HK) Company Limited"}], "name": "聚翰電子(重慶)有限公司", "no_holder": false, "taxcode": "NA"}, {"is_core": false, "source": [{"holder": "1", "name": "MEC Ultramax (HK) Company Limited"}], "name": "龍翰電子(蘇州)有限公司", "no_holder": false, "taxcode": "NA"}, {"is_core": false, "source": [{"holder": "1", "name": "MEC Best Known Company Limited"}], "name": "蘇州瀚騰電子科技有限公司", "no_holder": false, "taxcode": "NA"}], "links": [{"target": 1, "holder": "40.000000", "source": 0}, {"target": 3, "holder": "100.000000", "source": 2}, {"target": 5, "holder": "99.990000", "source": 4}, {"target": 7, "holder": "100.000000", "source": 6}, {"target": 9, "holder": "100.000000", "source": 8}, {"target": 10, "holder": "100.000000", "source": 8}, {"target": 12, "holder": "50.000000", "source": 11}, {"target": 13, "holder": "100.000000", "source": 8}, {"target": 2, "holder": "100.000000", "source": 8}, {"target": 11, "holder": "13.890000", "source": 4}, {"target": 11, "holder": "86.110000", "source": 14}, {"target": 15, "holder": "49.000000", "source": 8}, {"target": 16, "holder": "100.000000", "source": 4}, {"target": 6, "holder": "100.000000", "source": 4}, {"target": 8, "holder": "100.000000", "source": 14}, {"target": 17, "holder": "100.000000", "source": 8}, {"target": 18, "holder": "40.000000", "source": 8}, {"target": 4, "holder": "100.000000", "source": 14}, {"target": 19, "holder": "49.000000", "source": 8}, {"target": 21, "holder": "75.000000", "source": 20}, {"target": 22, "holder": "99.000000", "source": 8}, {"target": 23, "holder": "100.000000", "source": 8}, {"target": 24, "holder": "100.000000", "source": 22}, {"target": 26, "holder": "100.000000", "source": 25}, {"target": 25, "holder": "100.000000", "source": 8}, {"target": 27, "holder": "20.000000", "source": 20}, {"target": 27, "holder": "20.000000", "source": 11}, {"target": 27, "holder": "20.000000", "source": 16}, {"target": 27, "holder": "20.000000", "source": 6}, {"target": 27, "holder": "20.000000", "source": 14}, {"target": 28, "holder": "100.000000", "source": 4}, {"target": 30, "holder": "100.000000", "source": 29}, {"target": 32, "holder": "100.000000", "source": 31}, {"target": 33, "holder": "100.000000", "source": 31}, {"target": 29, "holder": "100.000000", "source": 31}, {"target": 0, "holder": "100.000000", "source": 31}, {"target": 34, "holder": "100.000000", "source": 0}, {"target": 31, "holder": "100.000000", "source": 35}, {"target": 36, "holder": "100.000000", "source": 31}, {"target": 14, "holder": "NA", "source": 37}, {"target": 38, "holder": "100.000000", "source": 5}, {"target": 39, "holder": "99.990000", "source": 5}, {"target": 40, "holder": "100.000000", "source": 5}, {"target": 41, "holder": "75.000000", "source": 5}, {"target": 42, "holder": "99.990000", "source": 14}, {"target": 43, "holder": "100.000000", "source": 30}, {"target": 44, "holder": "100.000000", "source": 33}, {"target": 45, "holder": "100.000000", "source": 36}, {"target": 46, "holder": "100.000000", "source": 32}, {"target": 35, "holder": "14.120000", "source": 37}], "y": "2014"}