{"target_list": {"威健實業股份有限公司": {"source_list": [{"holder": "NA", "name": "威記投資股份有限公司"}], "taxcode": "04648938"}, "Weitech International Co., Ltd.": {"source_list": [{"holder": "1", "name": "Weikeng International Co., Ltd."}], "taxcode": "NA"}, "Weikeng Technology Ptd. Ltd.": {"source_list": [{"holder": "1", "name": "威健實業股份有限公司"}], "taxcode": "NA"}, "威健國際貿易(上海)有限公司": {"source_list": [{"holder": "1", "name": "Weikeng International Co., Ltd."}], "taxcode": "NA"}, "Weikeng International Co., Ltd.": {"source_list": [{"holder": "1", "name": "威健實業股份有限公司"}], "taxcode": "NA"}, "威健資通股份有限公司": {"source_list": [{"holder": "1", "name": "威健實業股份有限公司"}], "taxcode": "23014408"}}, "company_list": [{"taxcode_source": "04648938", "target": "Weikeng International Co., Ltd.", "has_fine": false, "source": "威健實業股份有限公司", "holder": "1", "taxcode_target": "NA"}, {"taxcode_source": "04648938", "target": "Weikeng Technology Ptd. Ltd.", "has_fine": false, "source": "威健實業股份有限公司", "holder": "1", "taxcode_target": "NA"}, {"taxcode_source": "NA", "target": "Weitech International Co., Ltd.", "has_fine": false, "source": "Weikeng International Co., Ltd.", "holder": "1", "taxcode_target": "NA"}, {"taxcode_source": "NA", "target": "威健國際貿易(上海)有限公司", "has_fine": false, "source": "Weikeng International Co., Ltd.", "holder": "1", "taxcode_target": "NA"}, {"taxcode_source": "04648938", "target": "威健資通股份有限公司", "has_fine": false, "source": "威健實業股份有限公司", "holder": "1", "taxcode_target": "23014408"}, {"taxcode_source": "16162944", "target": "威健實業股份有限公司", "has_fine": false, "source": "威記投資股份有限公司", "holder": "NA", "taxcode_target": "04648938"}], "company_summery": {"has_fine": false, "fine_penalty_amount": 0, "company_amount": 7, "group_name": "威健", "fine_record_num": 0, "group_no": "G3033", "fine_company_amount": 0}, "fine_company_list": []}