{"nodes": [{"is_core": true, "source": [{"holder": "0.5901", "name": "群益金鼎證券股份有限公司"}, {"holder": "NA", "name": "閎業投資股份有限公司"}], "name": "群益期貨股份有限公司", "no_holder": false, "taxcode": "NA"}, {"is_core": false, "source": [{"holder": "0.49", "name": "群益期貨股份有限公司"}], "name": "志投顧問(香港)有限公司", "no_holder": false, "taxcode": "NA"}, {"is_core": false, "source": [{"holder": "1", "name": "金鼎綜合證券(維京)(股)公司"}], "name": "金鼎綜合證券(香港)有限公司", "no_holder": false, "taxcode": "NA"}, {"is_core": false, "source": [{"holder": "1", "name": "金鼎綜合證券(香港)有限公司"}], "name": "金鼎資本(香港)有限公司", "no_holder": false, "taxcode": "NA"}, {"is_core": false, "source": [{"holder": "1", "name": "群益金鼎證券股份有限公司"}], "name": "金鼎綜合證券(維京)(股)公司", "no_holder": false, "taxcode": "NA"}, {"is_core": true, "source": [{"holder": "NA", "name": "銀豐實業股份有限公司"}, {"holder": "NA", "name": "泰群實業股份有限公司"}, {"holder": "NA", "name": "鴻隆實業股份有限公司"}, {"holder": "NA", "name": "光星實業股份有限公司"}, {"holder": "NA", "name": "三河實業股份有限公司"}], "name": "群益金鼎證券股份有限公司", "no_holder": false, "taxcode": "NA"}, {"is_core": false, "source": [{"holder": "0.9999", "name": "群益金鼎證券股份有限公司"}], "name": "晶鼎股份有限公司", "no_holder": false, "taxcode": "84703356"}, {"is_core": false, "source": [{"holder": "0.9992", "name": "群益金鼎證券股份有限公司"}], "name": "群金股份有限公司", "no_holder": false, "taxcode": "84757900"}, {"is_core": false, "source": [{"holder": "1", "name": "群益金鼎證券股份有限公司"}], "name": "群益國際控股有限公司", "no_holder": false, "taxcode": "NA"}, {"is_core": false, "source": [{"holder": "1", "name": "群益國際控股有限公司"}], "name": "群益(香港)有限公司", "no_holder": false, "taxcode": "NA"}, {"is_core": false, "source": [{"holder": "1", "name": "群益期貨股份有限公司"}], "name": "群益國際資訊股份有限公司", "no_holder": false, "taxcode": "24782692"}, {"is_core": false, "source": [{"holder": "0.51", "name": "群益國際資訊股份有限公司"}], "name": "群益志投科技(成都)有限公司", "no_holder": false, "taxcode": "NA"}, {"is_core": false, "name": "銀豐實業股份有限公司", "no_holder": false, "taxcode": "23416254"}, {"is_core": false, "name": "泰群實業股份有限公司", "no_holder": false, "taxcode": "23416043"}, {"is_core": false, "name": "鴻隆實業股份有限公司", "no_holder": false, "taxcode": "23416326"}, {"is_core": false, "name": "光星實業股份有限公司", "no_holder": false, "taxcode": "75183902"}, {"is_core": false, "name": "三河實業股份有限公司", "no_holder": false, "taxcode": "12150637"}, {"is_core": false, "source": [{"holder": "1", "name": "群益金鼎證券股份有限公司"}], "name": "群益保險代理人股份有限公司", "no_holder": false, "taxcode": "12662932"}, {"is_core": false, "source": [{"holder": "1", "name": "群益金鼎證券股份有限公司"}], "name": "群益保險經紀人股份有限公司", "no_holder": false, "taxcode": "12663186"}, {"is_core": false, "source": [{"holder": "1", "name": "群益金鼎證券股份有限公司"}], "name": "群益創業投資股份有限公司", "no_holder": false, "taxcode": "24805127"}, {"is_core": false, "source": [{"holder": "0.9727", "name": "群益期貨股份有限公司"}, {"holder": "0.9727", "name": "群益(香港)有限公司"}], "name": "群益期貨(香港)有限公司", "no_holder": false, "taxcode": "NA"}, {"is_core": false, "source": [{"holder": "0.7", "name": "群益國際控股有限公司"}, {"holder": "0.3", "name": "群益(香港)有限公司"}], "name": "群益證券(香港)有限公司", "no_holder": false, "taxcode": "NA"}, {"is_core": false, "source": [{"holder": "1", "name": "群益金鼎證券股份有限公司"}], "name": "群益證券投資顧問股份有限公司", "no_holder": false, "taxcode": "23620951"}, {"is_core": false, "source": [{"holder": "1", "name": "群益證券(香港)有限公司"}], "name": "群益證券託管有限公司", "no_holder": false, "taxcode": "NA"}, {"is_core": false, "source": [{"holder": "1", "name": "群益國際資訊股份有限公司"}], "name": "上海群期資訊科技有限公司", "no_holder": false, "taxcode": "NA"}, {"is_core": false, "name": "閎業投資股份有限公司", "no_holder": false, "taxcode": "16742079"}], "links": [{"target": 1, "holder": "49.000000", "source": 0}, {"target": 3, "holder": "100.000000", "source": 2}, {"target": 2, "holder": "100.000000", "source": 4}, {"target": 4, "holder": "100.000000", "source": 5}, {"target": 6, "holder": "99.990000", "source": 5}, {"target": 7, "holder": "99.920000", "source": 5}, {"target": 9, "holder": "100.000000", "source": 8}, {"target": 11, "holder": "51.000000", "source": 10}, {"target": 5, "holder": "NA", "source": 12}, {"target": 5, "holder": "NA", "source": 13}, {"target": 5, "holder": "NA", "source": 14}, {"target": 5, "holder": "NA", "source": 15}, {"target": 5, "holder": "NA", "source": 16}, {"target": 17, "holder": "100.000000", "source": 5}, {"target": 18, "holder": "100.000000", "source": 5}, {"target": 8, "holder": "100.000000", "source": 5}, {"target": 10, "holder": "100.000000", "source": 0}, {"target": 19, "holder": "100.000000", "source": 5}, {"target": 20, "holder": "97.270000", "source": 0}, {"target": 20, "holder": "97.270000", "source": 9}, {"target": 0, "holder": "59.010000", "source": 5}, {"target": 21, "holder": "70.000000", "source": 8}, {"target": 21, "holder": "30.000000", "source": 9}, {"target": 22, "holder": "100.000000", "source": 5}, {"target": 23, "holder": "100.000000", "source": 21}, {"target": 24, "holder": "100.000000", "source": 10}, {"target": 0, "holder": "NA", "source": 25}], "y": "2016"}