{"nodes": [{"is_core": true, "source": [{"holder": "NA", "name": "KINGKONG DEVELOPMENT LLC"}], "name": "樂陞科技股份有限公司", "no_holder": false, "taxcode": "70834862"}, {"is_core": false, "source": [{"holder": "1", "name": "樂陞科技股份有限公司"}], "name": "More Than Tiny Limited", "no_holder": false, "taxcode": "NA"}, {"is_core": false, "source": [{"holder": "0.9", "name": "More Than Tiny Limited"}, {"holder": "0", "name": "樂陞科技股份有限公司"}], "name": "Proficient Success Limited", "no_holder": false, "taxcode": "NA"}, {"is_core": false, "source": [{"holder": "1", "name": "Proficient Success Limited"}], "name": "Tiny Piece Co., Ltd.", "no_holder": false, "taxcode": "NA"}, {"is_core": false, "source": [{"holder": "1", "name": "樂陞科技股份有限公司"}], "name": "一之鄉股份有限公司", "no_holder": false, "taxcode": "14004175"}, {"is_core": false, "source": [{"holder": "1", "name": "樂陞科技股份有限公司"}], "name": "方創投資有限公司", "no_holder": false, "taxcode": "54693269"}, {"is_core": false, "source": [{"holder": "0.7129", "name": "蘇州工業園區樂陞軟件有限公司"}], "name": "北京樂陞科技股份有限公司", "no_holder": false, "taxcode": "NA"}, {"is_core": false, "source": [{"holder": "1", "name": "北京樂陞科技股份有限公司"}], "name": "北京樂太科技有限公司", "no_holder": false, "taxcode": "NA"}, {"is_core": false, "source": [{"holder": "1", "name": "啟陞科技有限公司"}], "name": "蘇州工業園區樂陞軟件有限公司", "no_holder": false, "taxcode": "NA"}, {"is_core": false, "source": [{"holder": "0.817", "name": "樂陞科技股份有限公司"}], "name": "玩酷科技股份有限公司", "no_holder": false, "taxcode": "12950238"}, {"is_core": false, "source": [{"holder": "1", "name": "樂陞科技股份有限公司"}], "name": "啟陞科技有限公司", "no_holder": false, "taxcode": "NA"}, {"is_core": false, "source": [{"holder": "0.2308", "name": "樂陞科技股份有限公司"}], "name": "創夢市集股份有限公司", "no_holder": false, "taxcode": "54708657"}, {"is_core": false, "source": [{"holder": "1", "name": "一之鄉股份有限公司"}], "name": "萬達來富投資管理(香港)有限公司", "no_holder": false, "taxcode": "NA"}, {"is_core": false, "source": [{"holder": "0.49", "name": "樂陞科技股份有限公司"}], "name": "瘋糖數位科技股份有限公司", "no_holder": false, "taxcode": "24713680"}, {"is_core": false, "source": [{"holder": "0.1", "name": "樂陞科技股份有限公司"}], "name": "磁力線上股份有限公司", "no_holder": false, "taxcode": "53957642"}, {"is_core": false, "source": [{"holder": "1", "name": "一之鄉股份有限公司"}], "name": "蜜鄉有限公司", "no_holder": false, "taxcode": "53202048"}, {"is_core": false, "name": "KINGKONG DEVELOPMENT LLC", "no_holder": false, "taxcode": "NA"}, {"is_core": true, "source": [{"holder": "0.7543", "name": "樂陞科技股份有限公司"}], "name": "樂陞美術館股份有限公司", "no_holder": false, "taxcode": "29024918"}, {"is_core": false, "source": [{"holder": "1", "name": "樂陞美術館股份有限公司"}], "name": "樂陞美術中心有限公司", "no_holder": false, "taxcode": "NA"}, {"is_core": false, "source": [{"holder": "0.49", "name": "樂陞科技股份有限公司"}], "name": "糖蛙線上娛樂股份有限公司", "no_holder": false, "taxcode": "24966988"}, {"is_core": false, "source": [{"holder": "0.7143", "name": "玩酷科技股份有限公司"}], "name": "藍莓創意股份有限公司", "no_holder": false, "taxcode": "54845322"}, {"is_core": false, "source": [{"holder": "1", "name": "樂陞美術中心有限公司"}], "name": "蘇州工業園區樂美館軟件有限公司", "no_holder": false, "taxcode": "NA"}, {"is_core": false, "source": [{"holder": "0.3324", "name": "樂陞科技股份有限公司"}], "name": "蘑菇數位娛樂股份有限公司", "no_holder": false, "taxcode": "53520557"}], "links": [{"target": 1, "holder": "100.000000", "source": 0}, {"target": 2, "holder": "90.000000", "source": 1}, {"target": 2, "holder": "0.000000", "source": 0}, {"target": 3, "holder": "100.000000", "source": 2}, {"target": 4, "holder": "100.000000", "source": 0}, {"target": 5, "holder": "100.000000", "source": 0}, {"target": 7, "holder": "100.000000", "source": 6}, {"target": 6, "holder": "71.290000", "source": 8}, {"target": 9, "holder": "81.700000", "source": 0}, {"target": 10, "holder": "100.000000", "source": 0}, {"target": 11, "holder": "23.080000", "source": 0}, {"target": 12, "holder": "100.000000", "source": 4}, {"target": 13, "holder": "49.000000", "source": 0}, {"target": 14, "holder": "10.000000", "source": 0}, {"target": 15, "holder": "100.000000", "source": 4}, {"target": 0, "holder": "NA", "source": 16}, {"target": 18, "holder": "100.000000", "source": 17}, {"target": 17, "holder": "75.430000", "source": 0}, {"target": 19, "holder": "49.000000", "source": 0}, {"target": 20, "holder": "71.430000", "source": 9}, {"target": 21, "holder": "100.000000", "source": 18}, {"target": 8, "holder": "100.000000", "source": 10}, {"target": 22, "holder": "33.240000", "source": 0}], "y": "2015"}