{"nodes": [{"is_core": false, "source": [{"holder": "1", "name": "宜特科技股份有限公司"}], "name": "Samoa IST", "no_holder": false, "taxcode": "NA"}, {"is_core": false, "source": [{"holder": "1", "name": "Samoa IST"}], "name": "Brunei IST", "no_holder": false, "taxcode": "NA"}, {"is_core": false, "source": [{"holder": "0.88", "name": "宜特科技股份有限公司"}], "name": "Supreme Fortune Corp.", "no_holder": false, "taxcode": "NA"}, {"is_core": false, "source": [{"holder": "1", "name": "Supreme Fortune Corp."}], "name": "Hot Light Co., Ltd.", "no_holder": false, "taxcode": "NA"}, {"is_core": false, "source": [{"holder": "0.44", "name": "Samoa IST"}], "name": "IC Service Ltd.", "no_holder": false, "taxcode": "NA"}, {"is_core": false, "source": [{"holder": "1", "name": "Samoa IST"}], "name": "Innovative Service Technology Inc.", "no_holder": false, "taxcode": "NA"}, {"is_core": false, "source": [{"holder": "1", "name": "Samoa IST"}], "name": "Mauritius Ample Fortress Co ., Ltd.", "no_holder": false, "taxcode": "NA"}, {"is_core": true, "source": [{"holder": "NA", "name": "漢勝投資股份有限公司"}], "name": "宜特科技股份有限公司", "no_holder": false, "taxcode": "89845410"}, {"is_core": false, "source": [{"holder": "0.83", "name": "Hot Light Co., Ltd."}], "name": "昆山永續智財技術服務有限公司", "no_holder": false, "taxcode": "NA"}, {"is_core": false, "source": [{"holder": "1", "name": "昆山永續智財技術服務有限公司"}], "name": "永續高科技術服務(北京)有限公司", "no_holder": false, "taxcode": "NA"}, {"is_core": false, "source": [{"holder": "1", "name": "Hot Light Co., Ltd."}], "name": "永續智財有限公司", "no_holder": false, "taxcode": "42746987"}, {"is_core": false, "source": [{"holder": "0.25", "name": "Brunei IST"}, {"holder": "0.75", "name": "宜特科技(昆山)有限公司"}], "name": "宜特(上海)檢測技術有限公司", "no_holder": false, "taxcode": "NA"}, {"is_core": false, "source": [{"holder": "1", "name": "Brunei IST"}], "name": "宜特科技(昆山)有限公司", "no_holder": false, "taxcode": "NA"}, {"is_core": false, "name": "漢勝投資股份有限公司", "no_holder": false, "taxcode": "80102401"}, {"is_core": false, "source": [{"holder": "1", "name": "宜特科技股份有限公司"}], "name": "品文股份有限公司", "no_holder": false, "taxcode": "53039855"}, {"is_core": false, "source": [{"holder": "0", "name": "品文股份有限公司"}], "name": "宜智發科技股份有限公司", "no_holder": true, "taxcode": "80012648"}, {"is_core": false, "source": [{"holder": "0.85", "name": "宜特科技股份有限公司"}], "name": "宜準科技股份有限公司", "no_holder": false, "taxcode": "27270174"}, {"is_core": false, "source": [{"holder": "1", "name": "宜特科技(昆山)有限公司"}], "name": "宜碩科技(北京)有限公司", "no_holder": false, "taxcode": "NA"}, {"is_core": false, "source": [{"holder": "1", "name": "宜特科技(昆山)有限公司"}], "name": "深圳宜特檢測技術有限公司", "no_holder": false, "taxcode": "NA"}, {"is_core": false, "source": [{"holder": "0", "name": "宜特科技股份有限公司"}], "name": "德凱宜特股份有限公司", "no_holder": true, "taxcode": "53492406"}, {"is_core": false, "source": [{"holder": "0.33", "name": "宜特科技股份有限公司"}, {"holder": "0.07", "name": "品文股份有限公司"}], "name": "標準科技股份有限公司", "no_holder": false, "taxcode": "80299777"}], "links": [{"target": 1, "holder": "100.000000", "source": 0}, {"target": 3, "holder": "100.000000", "source": 2}, {"target": 4, "holder": "44.000000", "source": 0}, {"target": 5, "holder": "100.000000", "source": 0}, {"target": 6, "holder": "100.000000", "source": 0}, {"target": 0, "holder": "100.000000", "source": 7}, {"target": 2, "holder": "88.000000", "source": 7}, {"target": 9, "holder": "100.000000", "source": 8}, {"target": 10, "holder": "100.000000", "source": 3}, {"target": 11, "holder": "25.000000", "source": 1}, {"target": 11, "holder": "75.000000", "source": 12}, {"target": 12, "holder": "100.000000", "source": 1}, {"target": 7, "holder": "NA", "source": 13}, {"target": 15, "holder": "0.000000", "source": 14}, {"target": 16, "holder": "85.000000", "source": 7}, {"target": 17, "holder": "100.000000", "source": 12}, {"target": 8, "holder": "83.000000", "source": 3}, {"target": 14, "holder": "100.000000", "source": 7}, {"target": 18, "holder": "100.000000", "source": 12}, {"target": 19, "holder": "0.000000", "source": 7}, {"target": 20, "holder": "33.000000", "source": 7}, {"target": 20, "holder": "7.000000", "source": 14}], "y": "2015"}