{"target_list": {"至興精機股份有限公司": {"source_list": [{"holder": "NA", "name": "全道投資有限公司"}, {"holder": "NA", "name": "全泰投資股份有限公司"}, {"holder": "NA", "name": "福元投資股份有限公司"}, {"holder": "NA", "name": "全興投資開發股份有限公司"}], "taxcode": "22794503"}, "PROPITIOUS INTERNATIONAL INC.": {"source_list": [{"holder": "0.5575", "name": "至興精機股份有限公司"}], "taxcode": "NA"}, "SUPERIORITY ENTERPRISE CORP.": {"source_list": [{"holder": "1", "name": "至興精機股份有限公司"}], "taxcode": "NA"}, "蘇州昶興科技有限公司": {"source_list": [{"holder": "1", "name": "SUPERIORITY ENTERPRISE CORP."}], "taxcode": "NA"}, "蘇州昶興精密有限公司": {"source_list": [{"holder": "0", "name": "蘇州昶興科技有限公司"}], "taxcode": "NA"}, "GSK VIETNAM CO., LTD.": {"source_list": [{"holder": "1", "name": "PROPITIOUS INTERNATIONAL INC."}], "taxcode": "NA"}}, "company_list": [{"taxcode_source": "NA", "target": "GSK VIETNAM CO., LTD.", "has_fine": false, "source": "PROPITIOUS INTERNATIONAL INC.", "holder": "1", "taxcode_target": "NA"}, {"taxcode_source": "22794503", "target": "PROPITIOUS INTERNATIONAL INC.", "has_fine": false, "source": "至興精機股份有限公司", "holder": "0.5575", "taxcode_target": "NA"}, {"taxcode_source": "22794503", "target": "SUPERIORITY ENTERPRISE CORP.", "has_fine": false, "source": "至興精機股份有限公司", "holder": "1", "taxcode_target": "NA"}, {"taxcode_source": "27482418", "target": "至興精機股份有限公司", "has_fine": false, "source": "全道投資有限公司", "holder": "NA", "taxcode_target": "22794503"}, {"taxcode_source": "22656733", "target": "至興精機股份有限公司", "has_fine": false, "source": "全泰投資股份有限公司", "holder": "NA", "taxcode_target": "22794503"}, {"taxcode_source": "89331593", "target": "至興精機股份有限公司", "has_fine": false, "source": "福元投資股份有限公司", "holder": "NA", "taxcode_target": "22794503"}, {"taxcode_source": "22002609", "target": "至興精機股份有限公司", "has_fine": false, "source": "全興投資開發股份有限公司", "holder": "NA", "taxcode_target": "22794503"}, {"taxcode_source": "NA", "target": "蘇州昶興科技有限公司", "has_fine": false, "source": "SUPERIORITY ENTERPRISE CORP.", "holder": "1", "taxcode_target": "NA"}, {"taxcode_source": "NA", "target": "蘇州昶興精密有限公司", "has_fine": false, "source": "蘇州昶興科技有限公司", "holder": "0", "taxcode_target": "NA"}], "company_summery": {"has_fine": true, "fine_penalty_amount": 18000, "company_amount": 10, "group_name": "至興精機", "fine_record_num": 3, "group_no": "G4535", "fine_company_amount": 1}, "fine_company_list": [{"penalty_amount": 18000, "fine_num": 3, "name": "至興精機股份有限公司", "taxcode": "22794503"}]}