{"target_list": {"深圳岱桓貿易有限公司": {"source_list": [{"holder": "1", "name": "TOP WILL INTERNATIONAL LTD."}], "taxcode": "NA"}, "TOP WILL INTERNATIONAL LTD.": {"source_list": [{"holder": "1", "name": "岱煒科技股份有限公司"}], "taxcode": "NA"}}, "company_list": [{"taxcode_source": "12943883", "target": "TOP WILL INTERNATIONAL LTD.", "has_fine": false, "source": "岱煒科技股份有限公司", "holder": "1", "taxcode_target": "NA"}, {"taxcode_source": "NA", "target": "深圳岱桓貿易有限公司", "has_fine": false, "source": "TOP WILL INTERNATIONAL LTD.", "holder": "1", "taxcode_target": "NA"}], "company_summery": {"has_fine": false, "fine_penalty_amount": 0, "company_amount": 3, "group_name": "岱煒", "fine_record_num": 0, "group_no": "G6475", "fine_company_amount": 0}, "fine_company_list": []}