{"nodes": [{"is_core": true, "source": [{"holder": "NA", "name": "太陽創新投資股份有限公司"}, {"holder": "NA", "name": "尚緣開發投資有限公司"}], "name": "太陽光電能源科技股份有限公司", "no_holder": false, "taxcode": "28318416"}, {"is_core": false, "source": [{"holder": "1", "name": "太陽光電能源科技股份有限公司"}], "name": "BIG SUN GROUP LIMITED", "no_holder": false, "taxcode": "NA"}, {"is_core": false, "source": [{"holder": "1", "name": "太陽光電能源科技股份有限公司"}], "name": "上陽能源科技有限公司", "no_holder": false, "taxcode": "25023439"}, {"is_core": false, "source": [{"holder": "0", "name": "上陽能源科技有限公司"}], "name": "Topper Sun Energy Deutschland GmbH", "no_holder": true, "taxcode": "NA"}, {"is_core": false, "source": [{"holder": "1", "name": "上陽能源科技有限公司"}], "name": "Toppersun energy Japan Co., Ltd.", "no_holder": false, "taxcode": "NA"}, {"is_core": false, "source": [{"holder": "1", "name": "太陽光電能源科技股份有限公司"}], "name": "上昇陽光有限公司", "no_holder": false, "taxcode": "54805840"}, {"is_core": false, "source": [{"holder": "1", "name": "太陽光電能源科技股份有限公司"}], "name": "上富陽光有限公司", "no_holder": false, "taxcode": "54805927"}, {"is_core": false, "source": [{"holder": "0.5", "name": "太陽全球投資股份有限公司"}], "name": "太一事業有限公司", "no_holder": false, "taxcode": "29045955"}, {"is_core": false, "source": [{"holder": "0.5", "name": "太一事業有限公司"}], "name": "千太陽光科技股份有限公司", "no_holder": false, "taxcode": "53861626"}, {"is_core": false, "source": [{"holder": "0.5", "name": "太一事業有限公司"}], "name": "中太陽光科技股份有限公司", "no_holder": false, "taxcode": "53861533"}, {"is_core": false, "source": [{"holder": "0.9241", "name": "太陽光電能源科技股份有限公司"}], "name": "太陽全球投資股份有限公司", "no_holder": false, "taxcode": "53497991"}, {"is_core": false, "source": [{"holder": "1", "name": "太陽光電能源科技股份有限公司"}], "name": "太上陽光有限公司", "no_holder": false, "taxcode": "54805996"}, {"is_core": false, "source": [{"holder": "1", "name": "太陽光電能源科技股份有限公司"}], "name": "太日陽光有限公司", "no_holder": false, "taxcode": "54772600"}, {"is_core": false, "source": [{"holder": "1", "name": "太陽光電能源科技股份有限公司"}], "name": "太弘陽光有限公司", "no_holder": false, "taxcode": "54547739"}, {"is_core": false, "source": [{"holder": "1", "name": "太陽光電能源科技股份有限公司"}], "name": "太全陽光有限公司", "no_holder": false, "taxcode": "54547941"}, {"is_core": false, "source": [{"holder": "0.5", "name": "太陽光電能源科技股份有限公司"}], "name": "太吉企業有限公司", "no_holder": false, "taxcode": "54242292"}, {"is_core": false, "source": [{"holder": "1", "name": "太陽光電能源科技股份有限公司"}], "name": "太昇陽光有限公司", "no_holder": false, "taxcode": "54772480"}, {"is_core": false, "source": [{"holder": "1", "name": "太陽光電能源科技股份有限公司"}], "name": "太昌企業有限公司", "no_holder": false, "taxcode": "54539512"}, {"is_core": false, "source": [{"holder": "1", "name": "太陽光電能源科技股份有限公司"}], "name": "太昱陽光有限公司", "no_holder": false, "taxcode": "54547800"}, {"is_core": false, "source": [{"holder": "1", "name": "太陽光電能源科技股份有限公司"}], "name": "太喜有限公司", "no_holder": false, "taxcode": "54242032"}, {"is_core": false, "name": "太陽創新投資股份有限公司", "no_holder": false, "taxcode": "53360051"}, {"is_core": false, "name": "尚緣開發投資有限公司", "no_holder": false, "taxcode": "24226176"}, {"is_core": false, "source": [{"holder": "1", "name": "太陽光電能源科技股份有限公司"}], "name": "太陽寶島電業股份有限公司", "no_holder": false, "taxcode": "45108842"}, {"is_core": false, "source": [{"holder": "1", "name": "太陽光電能源科技股份有限公司"}], "name": "太農生技有限公司", "no_holder": false, "taxcode": "53864617"}, {"is_core": false, "source": [{"holder": "1", "name": "太陽光電能源科技股份有限公司"}], "name": "太碩陽光有限公司", "no_holder": false, "taxcode": "54772539"}, {"is_core": false, "source": [{"holder": "1", "name": "太陽光電能源科技股份有限公司"}], "name": "太福企業有限公司", "no_holder": false, "taxcode": "54539631"}, {"is_core": false, "source": [{"holder": "1", "name": "太陽光電能源科技股份有限公司"}], "name": "太鑽陽光有限公司", "no_holder": false, "taxcode": "54547956"}, {"is_core": false, "source": [{"holder": "1", "name": "太陽光電能源科技股份有限公司"}], "name": "日太陽光有限公司", "no_holder": false, "taxcode": "54772550"}, {"is_core": false, "source": [{"holder": "1", "name": "BIG SUN GROUP LIMITED"}], "name": "巨陽(上海)電子科技有限公司", "no_holder": false, "taxcode": "NA"}, {"is_core": false, "source": [{"holder": "1", "name": "太陽光電能源科技股份有限公司"}], "name": "弘太陽光有限公司", "no_holder": false, "taxcode": "54772469"}, {"is_core": false, "source": [{"holder": "1", "name": "太陽光電能源科技股份有限公司"}], "name": "全太陽光有限公司", "no_holder": false, "taxcode": "54772496"}, {"is_core": false, "source": [{"holder": "1", "name": "太陽光電能源科技股份有限公司"}], "name": "昇太陽光有限公司", "no_holder": false, "taxcode": "54772622"}, {"is_core": false, "source": [{"holder": "1", "name": "太陽光電能源科技股份有限公司"}], "name": "景上陽光有限公司", "no_holder": false, "taxcode": "54805855"}, {"is_core": false, "source": [{"holder": "1", "name": "太陽光電能源科技股份有限公司"}], "name": "詠太陽光有限公司", "no_holder": false, "taxcode": "54772518"}, {"is_core": false, "source": [{"holder": "1", "name": "太陽光電能源科技股份有限公司"}], "name": "福上陽光有限公司", "no_holder": false, "taxcode": "54806192"}], "links": [{"target": 1, "holder": "100.000000", "source": 0}, {"target": 3, "holder": "0.000000", "source": 2}, {"target": 4, "holder": "100.000000", "source": 2}, {"target": 5, "holder": "100.000000", "source": 0}, {"target": 6, "holder": "100.000000", "source": 0}, {"target": 2, "holder": "100.000000", "source": 0}, {"target": 8, "holder": "50.000000", "source": 7}, {"target": 9, "holder": "50.000000", "source": 7}, {"target": 7, "holder": "50.000000", "source": 10}, {"target": 11, "holder": "100.000000", "source": 0}, {"target": 12, "holder": "100.000000", "source": 0}, {"target": 13, "holder": "100.000000", "source": 0}, {"target": 14, "holder": "100.000000", "source": 0}, {"target": 15, "holder": "50.000000", "source": 0}, {"target": 16, "holder": "100.000000", "source": 0}, {"target": 17, "holder": "100.000000", "source": 0}, {"target": 18, "holder": "100.000000", "source": 0}, {"target": 19, "holder": "100.000000", "source": 0}, {"target": 0, "holder": "NA", "source": 20}, {"target": 0, "holder": "NA", "source": 21}, {"target": 10, "holder": "92.410000", "source": 0}, {"target": 22, "holder": "100.000000", "source": 0}, {"target": 23, "holder": "100.000000", "source": 0}, {"target": 24, "holder": "100.000000", "source": 0}, {"target": 25, "holder": "100.000000", "source": 0}, {"target": 26, "holder": "100.000000", "source": 0}, {"target": 27, "holder": "100.000000", "source": 0}, {"target": 28, "holder": "100.000000", "source": 1}, {"target": 29, "holder": "100.000000", "source": 0}, {"target": 30, "holder": "100.000000", "source": 0}, {"target": 31, "holder": "100.000000", "source": 0}, {"target": 32, "holder": "100.000000", "source": 0}, {"target": 33, "holder": "100.000000", "source": 0}, {"target": 34, "holder": "100.000000", "source": 0}], "y": "2016"}