{"nodes": [{"is_core": true, "source": [{"holder": "NA", "name": "建芃投資股份有限公司"}, {"holder": "NA", "name": "永業投資股份有限公司"}, {"holder": "NA", "name": "順楹投資股份有限公司"}, {"holder": "NA", "name": "鴻錦投資有限公司"}], "name": "育富電子股份有限公司", "no_holder": false, "taxcode": "45082694"}, {"is_core": false, "source": [{"holder": "1", "name": "育富電子股份有限公司"}], "name": "YUFO ELECTRONIC (BVI) LTD.", "no_holder": false, "taxcode": "NA"}, {"is_core": false, "name": "建芃投資股份有限公司", "no_holder": false, "taxcode": "27566319"}, {"is_core": false, "name": "永業投資股份有限公司", "no_holder": false, "taxcode": "NA"}, {"is_core": false, "name": "順楹投資股份有限公司", "no_holder": false, "taxcode": "80596122"}, {"is_core": false, "name": "鴻錦投資有限公司", "no_holder": false, "taxcode": "28138358"}, {"is_core": false, "source": [{"holder": "1", "name": "YUFO ELECTRONIC (BVI) LTD."}], "name": "鼎富電子(惠州)有限公司", "no_holder": false, "taxcode": "NA"}], "links": [{"target": 1, "holder": "100.000000", "source": 0}, {"target": 0, "holder": "NA", "source": 2}, {"target": 0, "holder": "NA", "source": 3}, {"target": 0, "holder": "NA", "source": 4}, {"target": 0, "holder": "NA", "source": 5}, {"target": 6, "holder": "100.000000", "source": 1}], "y": "2014"}