{"nodes": [{"is_core": true, "source": [{"holder": "NA", "name": "華龍財務顧問股份有限公司"}, {"holder": "NA", "name": "鹿寮坑股份有限公司"}], "name": "順達科技股份有限公司", "no_holder": false, "taxcode": "16596982"}, {"is_core": false, "source": [{"holder": "1", "name": "順達科技股份有限公司"}], "name": "Dynapack Technologies (Cayman) Corporation", "no_holder": false, "taxcode": "NA"}, {"is_core": false, "source": [{"holder": "1", "name": "Dynapack Technologies (Cayman) Corporation"}], "name": "順達科技(香港)股份有限公司", "no_holder": false, "taxcode": "NA"}, {"is_core": false, "source": [{"holder": "1", "name": "順達科技(香港)股份有限公司"}], "name": "昆山順陽電子科技有限公司", "no_holder": false, "taxcode": "NA"}, {"is_core": false, "source": [{"holder": "0.3", "name": "順達科技股份有限公司"}], "name": "致禾順開發股份有限公司", "no_holder": false, "taxcode": "53833431"}, {"is_core": false, "source": [{"holder": "1", "name": "順達科技股份有限公司"}], "name": "順陽投資股份有限公司", "no_holder": false, "taxcode": "25132865"}, {"is_core": false, "name": "華龍財務顧問股份有限公司", "no_holder": false, "taxcode": "12866561"}, {"is_core": false, "name": "鹿寮坑股份有限公司", "no_holder": false, "taxcode": "28459409"}, {"is_core": false, "source": [{"holder": "1", "name": "順達科技(香港)股份有限公司"}], "name": "順達電子科技(蘇州)有限公司", "no_holder": false, "taxcode": "NA"}], "links": [{"target": 1, "holder": "100.000000", "source": 0}, {"target": 3, "holder": "100.000000", "source": 2}, {"target": 4, "holder": "30.000000", "source": 0}, {"target": 5, "holder": "100.000000", "source": 0}, {"target": 2, "holder": "100.000000", "source": 1}, {"target": 0, "holder": "NA", "source": 6}, {"target": 0, "holder": "NA", "source": 7}, {"target": 8, "holder": "100.000000", "source": 2}], "y": "2015"}