{"target_list": {"THUNDER TIGER EUROPE GMBH": {"source_list": [{"holder": "1", "name": "雷虎科技股份有限公司"}], "taxcode": "NA"}, "UPTOP LTD.": {"source_list": [{"holder": "1", "name": "THUNDER TIGER MODEL (B.V.I) CO., LTD."}], "taxcode": "NA"}, "ACE HOBBY, INC.": {"source_list": [{"holder": "1", "name": "THUNDER TIGER (USA) CORP."}], "taxcode": "NA"}, "雷虎生技股份有限公司": {"source_list": [{"holder": "0.6786", "name": "雷虎科技股份有限公司"}], "taxcode": "53835304"}, "雷虎機電股份有限公司": {"source_list": [{"holder": "1", "name": "雷虎科技股份有限公司"}], "taxcode": "54759487"}, "雷祥生技股份有限公司": {"source_list": [{"holder": "0.49", "name": "雷虎生技股份有限公司"}], "taxcode": "54593120"}, "ASSOCIATED ELECTRICS, INC.": {"source_list": [{"holder": "1", "name": "THUNDER TIGER (USA) CORP."}], "taxcode": "NA"}, "雷虎(寧波)科技有限公司": {"source_list": [{"holder": "1", "name": "THUNDER TIGER MODEL (B.V.I) CO., LTD."}], "taxcode": "NA"}, "上海雷虎商貿有限公司": {"source_list": [{"holder": "1", "name": "雷虎(寧波)科技有限公司"}], "taxcode": "NA"}, "THUNDER TIGER MODEL (B.V.I) CO., LTD.": {"source_list": [{"holder": "1", "name": "雷虎科技股份有限公司"}], "taxcode": "NA"}, "THUNDER TIGER (USA) CORP.": {"source_list": [{"holder": "1", "name": "MANFORD INVESTMENTS LTD."}], "taxcode": "NA"}, "MANFORD INVESTMENTS LTD.": {"source_list": [{"holder": "1", "name": "雷虎科技股份有限公司"}], "taxcode": "NA"}, "GOLDEN MIRAGE CO.": {"source_list": [{"holder": "1", "name": "UPTOP LTD."}], "taxcode": "NA"}}, "company_list": [{"taxcode_source": "NA", "target": "ACE HOBBY, INC.", "has_fine": false, "source": "THUNDER TIGER (USA) CORP.", "holder": "1", "taxcode_target": "NA"}, {"taxcode_source": "NA", "target": "ASSOCIATED ELECTRICS, INC.", "has_fine": false, "source": "THUNDER TIGER (USA) CORP.", "holder": "1", "taxcode_target": "NA"}, {"taxcode_source": "NA", "target": "GOLDEN MIRAGE CO.", "has_fine": false, "source": "UPTOP LTD.", "holder": "1", "taxcode_target": "NA"}, {"taxcode_source": "52541175", "target": "MANFORD INVESTMENTS LTD.", "has_fine": false, "source": "雷虎科技股份有限公司", "holder": "1", "taxcode_target": "NA"}, {"taxcode_source": "NA", "target": "THUNDER TIGER (USA) CORP.", "has_fine": false, "source": "MANFORD INVESTMENTS LTD.", "holder": "1", "taxcode_target": "NA"}, {"taxcode_source": "52541175", "target": "THUNDER TIGER EUROPE GMBH", "has_fine": false, "source": "雷虎科技股份有限公司", "holder": "1", "taxcode_target": "NA"}, {"taxcode_source": "52541175", "target": "THUNDER TIGER MODEL (B.V.I) CO., LTD.", "has_fine": false, "source": "雷虎科技股份有限公司", "holder": "1", "taxcode_target": "NA"}, {"taxcode_source": "NA", "target": "UPTOP LTD.", "has_fine": false, "source": "THUNDER TIGER MODEL (B.V.I) CO., LTD.", "holder": "1", "taxcode_target": "NA"}, {"taxcode_source": "NA", "target": "上海雷虎商貿有限公司", "has_fine": false, "source": "雷虎(寧波)科技有限公司", "holder": "1", "taxcode_target": "NA"}, {"taxcode_source": "NA", "target": "雷虎(寧波)科技有限公司", "has_fine": false, "source": "THUNDER TIGER MODEL (B.V.I) CO., LTD.", "holder": "1", "taxcode_target": "NA"}, {"taxcode_source": "52541175", "target": "雷虎生技股份有限公司", "has_fine": false, "source": "雷虎科技股份有限公司", "holder": "0.6786", "taxcode_target": "53835304"}, {"taxcode_source": "52541175", "target": "雷虎機電股份有限公司", "has_fine": false, "source": "雷虎科技股份有限公司", "holder": "1", "taxcode_target": "54759487"}, {"taxcode_source": "53835304", "target": "雷祥生技股份有限公司", "has_fine": false, "source": "雷虎生技股份有限公司", "holder": "0.49", "taxcode_target": "54593120"}], "company_summery": {"has_fine": false, "fine_penalty_amount": 0, "company_amount": 14, "group_name": "雷虎科技", "fine_record_num": 0, "group_no": "G8033", "fine_company_amount": 0}, "fine_company_list": []}